backpack/__init__.py
backpack/cache.py
backpack/custom_errors.py
backpack/file_utils.py
backpack/folder_utils.py
backpack/json_metadata.py
backpack/json_user_settings.py
backpack/json_utils.py
backpack/logger.py
backpack/patterns.py
backpack/strings.py
backpack/test_utils.py
backpack/version.py
python_backpack-1.1.4.dist-info/LICENSE
python_backpack-1.1.4.dist-info/METADATA
python_backpack-1.1.4.dist-info/WHEEL
python_backpack-1.1.4.dist-info/RECORD
