Metadata-Version: 2.1
Name: python-backpack
Version: 1.1.4
Summary: A collection of personal scripts for json, File/Folder Operations, String Validation, Custom Errors, Cache and stuff.
Author: Maximiliano Rocamora
Requires-Python: >=3.9,<4.0
Classifier: Programming Language :: Python :: 3
Classifier: Programming Language :: Python :: 3.9
Classifier: Programming Language :: Python :: 3.10
Classifier: Programming Language :: Python :: 3.11
Classifier: Programming Language :: Python :: 3.12
Classifier: Programming Language :: Python :: 3.13
